profiling/entityhub/__init__.py
profiling/entityhub/modules.py
profiling/gedaif/__init__.py
profiling/gedaif/gsymlib.py
profiling/sourcing/__init__.py
profiling/sourcing/customs.py
profiling/sourcing/vendors.py
tendril/__init__.py
tendril/_version.py
tendril/main.py
tendril/runserver.py
tendril/auth/__init__.py
tendril/auth/roots.py
tendril/auth/users.py
tendril/auth/db/__init__.py
tendril/auth/db/controller.py
tendril/auth/db/model.py
tendril/boms/__init__.py
tendril/boms/configbase.py
tendril/boms/costingbase.py
tendril/boms/electronics.py
tendril/boms/entitybase.py
tendril/boms/outputbase.py
tendril/boms/products.py
tendril/boms/validate.py
tendril/conventions/__init__.py
tendril/conventions/electronics.py
tendril/conventions/series.py
tendril/conventions/status.py
tendril/conventions/motifs/DLPF1.py
tendril/conventions/motifs/ING_AD8421.py
tendril/conventions/motifs/LM3150.py
tendril/conventions/motifs/LPF1.py
tendril/conventions/motifs/LREGS1.py
tendril/conventions/motifs/__init__.py
tendril/conventions/motifs/ingbase.py
tendril/conventions/motifs/motifbase.py
tendril/dox/__init__.py
tendril/dox/customs.py
tendril/dox/docstore.py
tendril/dox/gedaproject.py
tendril/dox/indent.py
tendril/dox/invoice.py
tendril/dox/labelmaker.py
tendril/dox/production.py
tendril/dox/purchaseorder.py
tendril/dox/render.py
tendril/dox/testing.py
tendril/dox/wallet.py
tendril/dox/db/__init__.py
tendril/dox/db/controller.py
tendril/dox/db/model.py
tendril/dox/templates/geda-bom-simple.tex
tendril/dox/templates/indent_stock_template.tex
tendril/dox/templates/label_stock_template.tex
tendril/dox/templates/pcb-assem-manifest.tex
tendril/dox/templates/po_csil_template.tex
tendril/dox/templates/production-order-template.tex
tendril/dox/templates/customs/authorization.dhl.tex
tendril/dox/templates/customs/authorization.fedex.tex
tendril/dox/templates/customs/decl.tex
tendril/dox/templates/customs/rsp-declaration.tex
tendril_framework-0.1.0.dist-info/DESCRIPTION.rst
tendril_framework-0.1.0.dist-info/METADATA
tendril_framework-0.1.0.dist-info/RECORD
tendril_framework-0.1.0.dist-info/WHEEL
tendril_framework-0.1.0.dist-info/entry_points.txt
tendril_framework-0.1.0.dist-info/metadata.json
tendril_framework-0.1.0.dist-info/pbr.json
tendril_framework-0.1.0.dist-info/top_level.txt
