Metadata-Version: 2.0
Name: tendril-framework
Version: 0.1.0
Summary: An open-ended framework for handling information, to aid development, management, and production cycles
Home-page: https://github.com/chintal/tendril
Author: Chintalagiri Shashank
Author-email: shashank@chintal.in
License: AGPLv3
Platform: any
Classifier: Development Status :: 3 - Alpha
Classifier: Topic :: Scientific/Engineering :: Human Machine Interfaces
Classifier: Topic :: Scientific/Engineering :: Electronic Design Automation (EDA)
Classifier: Topic :: Office/Business
Classifier: Topic :: Utilities
Classifier: License :: OSI Approved :: GNU Affero General Public License v3 or later (AGPLv3+)
Classifier: Framework :: Flask
Classifier: Framework :: Twisted
Classifier: Intended Audience :: Science/Research
Classifier: Natural Language :: English
Classifier: Operating System :: OS Independent
Requires-Dist: Flask
Requires-Dist: Flask-Analytics
Requires-Dist: Flask-Assets
Requires-Dist: Flask-Login
Requires-Dist: Flask-Migrate
Requires-Dist: Flask-Principal
Requires-Dist: Flask-User
Requires-Dist: PyPDF2
Requires-Dist: SQLAlchemy
Requires-Dist: alembic
Requires-Dist: appenlight-client
Requires-Dist: argparse
Requires-Dist: arrow
Requires-Dist: beautifulsoup4
Requires-Dist: cachecontrol[filecache]
Requires-Dist: cachetools
Requires-Dist: colorama
Requires-Dist: cssmin
Requires-Dist: driver2200087
Requires-Dist: fs
Requires-Dist: future
Requires-Dist: idstring
Requires-Dist: iec60063
Requires-Dist: jinja2
Requires-Dist: jsmin
Requires-Dist: lxml
Requires-Dist: matplotlib
Requires-Dist: mistune
Requires-Dist: paramiko
Requires-Dist: pcb-tools
Requires-Dist: pillow
Requires-Dist: progress
Requires-Dist: psycopg2
Requires-Dist: pyhull
Requires-Dist: pyyaml
Requires-Dist: qrcode
Requires-Dist: requests
Requires-Dist: scipy
Requires-Dist: splinter
Requires-Dist: sqlalchemy-utils
Requires-Dist: suds
Requires-Dist: svn
Requires-Dist: tendril-gedaif-sym2eps
Requires-Dist: versioneer
Requires-Dist: watchdog
Requires-Dist: wtforms-components
Provides-Extra: doc
Requires-Dist: sphinx; extra == 'doc'
Requires-Dist: sphinx-argparse; extra == 'doc'
Requires-Dist: sphinx-rtd-theme; extra == 'doc'
Requires-Dist: sphinxcontrib-documentedlist; extra == 'doc'
Requires-Dist: sphinxcontrib-googleanalytics; extra == 'doc'
Requires-Dist: sphinxcontrib-sqlalchemyviz; extra == 'doc'
Requires-Dist: versioneer; extra == 'doc'
Provides-Extra: package
Requires-Dist: twine; extra == 'package'
Requires-Dist: wheel; extra == 'package'
Provides-Extra: test
Requires-Dist: pytest; extra == 'test'
